{"v":"5.12.1","fr":24,"ip":0,"op":36,"w":591,"h":120,"nm":"p","assets":[],"fonts":{"list":[{"fName":"Gilroy-ExtraBold","fFamily":"Gilroy","fStyle":"ExtraBold","ascent":70}]},"layers":[{"ind":1,"ty":3,"nm":"n","sr":1,"ks":{"o":{"a":0,"k":0},"r":{"a":0,"k":0},"p":{"a":0,"k":[295.5,60,0],"l":2},"a":{"a":0,"k":[50,50,0],"l":2},"s":{"a":0,"k":[100,100,100],"l":2}},"ao":0,"ip":0,"op":241,"st":0},{"ind":2,"ty":5,"nm":"F","parent":1,"sr":1,"ks":{"o":{"a":0,"k":100},"r":{"a":0,"k":0},"p":{"a":0,"k":[53,28.758,0],"l":2},"a":{"a":0,"k":[0.762,-6.614,0],"l":2},"s":{"a":0,"k":[100,100,100],"l":2}},"ao":0,"t":{"d":{"k":[{"s":{"s":20,"f":"Gilroy-ExtraBold","t":"Fact : Weâre secret society since 90âs","ca":0,"j":2,"tr":20,"lh":24,"ls":0,"fc":[0.259,0.258,0.258]},"t":0}]},"p":{},"m":{"g":1,"a":{"a":0,"k":[0,0]}},"a":[]},"ip":0,"op":241,"st":0,"ct":1},{"ind":3,"ty":4,"nm":"l","parent":1,"tt":1,"tp":4,"sr":1,"ks":{"o":{"a":0,"k":100},"r":{"a":0,"k":0},"p":{"a":1,"k":[{"i":{"x":0.281,"y":1},"o":{"x":0.356,"y":0},"t":0,"s":[-424,65.742,0],"to":[0,0,0],"ti":[0,0,0]},{"t":27,"s":[52,65.742,0]}],"l":2},"a":{"a":0,"k":[0,225,0],"l":2},"s":{"a":0,"k":[82.768,80,100],"l":2}},"ao":0,"shapes":[{"ty":"gr","it":[{"ty":"rc","d":1,"s":{"a":0,"k":[578,38]},"p":{"a":0,"k":[0,0]},"r":{"a":0,"k":20},"nm":"R"},{"ty":"fl","c":{"a":0,"k":[0.443,0.443,0.443,1]},"o":{"a":0,"k":100},"r":1,"nm":"F"},{"ty":"tr","p":{"a":0,"k":[0,225]},"a":{"a":0,"k":[0,0]},"s":{"a":0,"k":[100,100]},"r":{"a":0,"k":0},"o":{"a":0,"k":100},"sk":{"a":0,"k":0},"sa":{"a":0,"k":0},"nm":"T"}],"nm":"R"}],"ip":0,"op":38,"st":0,"ct":1},{"ind":4,"ty":4,"nm":"l","parent":1,"td":1,"sr":1,"ks":{"o":{"a":0,"k":100},"r":{"a":0,"k":0},"p":{"a":0,"k":[50,65.742,0],"l":2},"a":{"a":0,"k":[0,225,0],"l":2},"s":{"a":0,"k":[80,80,100],"l":2}},"ao":0,"shapes":[{"ty":"gr","it":[{"ty":"rc","d":1,"s":{"a":0,"k":[578,38]},"p":{"a":0,"k":[0,0]},"r":{"a":0,"k":20},"nm":"R"},{"ty":"fl","c":{"a":0,"k":[0.204,0.202,0.202,1]},"o":{"a":0,"k":100},"r":1,"nm":"F"},{"ty":"tr","p":{"a":0,"k":[0,225]},"a":{"a":0,"k":[0,0]},"s":{"a":0,"k":[100,100]},"r":{"a":0,"k":0},"o":{"a":0,"k":100},"sk":{"a":0,"k":0},"sa":{"a":0,"k":0},"nm":"T"}],"nm":"R"}],"ip":0,"op":40,"st":0,"ct":1},{"ind":5,"ty":4,"nm":"l","parent":1,"sr":1,"ks":{"o":{"a":0,"k":100},"r":{"a":0,"k":0},"p":{"a":0,"k":[50,65.742,0],"l":2},"a":{"a":0,"k":[0,225,0],"l":2},"s":{"a":0,"k":[80,80,100],"l":2}},"ao":0,"shapes":[{"ty":"gr","it":[{"ty":"rc","d":1,"s":{"a":0,"k":[578,38]},"p":{"a":0,"k":[0,0]},"r":{"a":0,"k":20},"nm":"R"},{"ty":"fl","c":{"a":0,"k":[0.204,0.202,0.202,1]},"o":{"a":0,"k":100},"r":1,"nm":"F"},{"ty":"tr","p":{"a":0,"k":[0,225]},"a":{"a":0,"k":[0,0]},"s":{"a":0,"k":[100,100]},"r":{"a":0,"k":0},"o":{"a":0,"k":100},"sk":{"a":0,"k":0},"sa":{"a":0,"k":0},"nm":"T"}],"nm":"R"}],"ip":0,"op":39,"st":0,"ct":1}],"markers":[],"chars":[{"ch":"F","size":20,"style":"ExtraBold","w":52,"data":{"shapes":[{"ty":"gr","it":[{"ind":0,"ty":"sh","ks":{"a":0,"k":{"i":[[0,0],[0,0],[0,0],[0,0],[0,0],[0,0],[0,0],[0,0],[0,0],[0,0]],"o":[[0,0],[0,0],[0,0],[0,0],[0,0],[0,0],[0,0],[0,0],[0,0],[0,0]],"v":[[48.843,-54.987],[48.843,-70.496],[6.042,-70.496],[6.042,0],[22.156,0],[22.156,-25.882],[48.34,-25.882],[48.34,-41.391],[22.156,-41.391],[22.156,-54.987]],"c":true}},"nm":"F"}],"nm":"F"}]},"fFamily":"Gilroy"},{"ch":"a","size":20,"style":"ExtraBold","w":62.3,"data":{"shapes":[{"ty":"gr","it":[{"ind":0,"ty":"sh","ks":{"a":0,"k":{"i":[[0,0],[0,0],[6.747,0],[0,-15.005],[-13.193,0],[-3.323,3.827],[0,0],[0,0],[0,0]],"o":[[0,0],[-3.323,-3.827],[-13.193,0],[0,15.005],[6.747,0],[0,0],[0,0],[0,0],[0,0]],"v":[[42.096,-50.354],[42.096,-45.621],[27.09,-51.764],[3.021,-25.177],[27.09,1.41],[42.096,-4.733],[42.096,0],[57.202,0],[57.202,-50.354]],"c":true}},"nm":"a"},{"ind":1,"ty":"sh","ks":{"a":0,"k":{"i":[[6.949,0],[0,7.553],[-6.949,0],[0,-7.553]],"o":[[-6.949,0],[0,-7.553],[6.949,0],[0,7.553]],"v":[[30.112,-12.891],[18.127,-25.177],[30.112,-37.463],[42.096,-25.177]],"c":true}},"nm":"a"}],"nm":"a"}]},"fFamily":"Gilroy"},{"ch":"c","size":20,"style":"ExtraBold","w":51.6,"data":{"shapes":[{"ty":"gr","it":[{"ind":0,"ty":"sh","ks":{"a":0,"k":{"i":[[-15.308,0],[-4.33,7.855],[0,0],[4.431,0],[0,6.949],[-6.546,0],[-1.712,-3.525],[0,0],[9.769,0],[0,-15.005]],"o":[[9.869,0],[0,0],[-1.611,3.525],[-6.546,0],[0,-6.949],[4.431,0],[0,0],[-4.33,-7.755],[-15.308,0],[0,15.005]],"v":[[29.709,1.41],[52.469,-11.581],[39.276,-19.135],[29.507,-13.495],[18.127,-25.177],[29.507,-36.859],[39.276,-31.219],[52.469,-38.873],[29.709,-51.764],[3.021,-25.177]],"c":true}},"nm":"c"}],"nm":"c"}]},"fFamily":"Gilroy"},{"ch":"t","size":20,"style":"ExtraBold","w":36.3,"data":{"shapes":[{"ty":"gr","it":[{"ind":0,"ty":"sh","ks":{"a":0,"k":{"i":[[0,0],[0,0],[0,0],[0,0],[0,0],[0,0],[0,0],[0,0],[0,0],[0,0],[-19.739,2.014],[0,0],[0,4.33],[0,0]],"o":[[0,0],[0,0],[0,0],[0,0],[0,0],[0,0],[0,0],[0,0],[0,0],[0,14.099],[0,0],[-6.647,0.403],[0,0],[0,0]],"v":[[35.046,-35.852],[35.046,-50.354],[24.673,-50.354],[24.673,-64.453],[9.567,-59.921],[9.567,-50.354],[1.511,-50.354],[1.511,-35.852],[9.567,-35.852],[9.567,-18.027],[35.046,0],[35.046,-13.696],[24.673,-18.027],[24.673,-35.852]],"c":true}},"nm":"t"}],"nm":"t"}]},"fFamily":"Gilroy"},{"ch":" ","size":20,"style":"ExtraBold","w":25,"data":{},"fFamily":"Gilroy"},{"ch":":","size":20,"style":"ExtraBold","w":28,"data":{"shapes":[{"ty":"gr","it":[{"ind":0,"ty":"sh","ks":{"a":0,"k":{"i":[[-5.237,0],[0,5.237],[5.237,0],[0,-5.237]],"o":[[5.237,0],[0,-5.237],[-5.237,0],[0,5.237]],"v":[[14.099,-32.831],[23.666,-42.398],[14.099,-51.965],[4.532,-42.398]],"c":true}},"nm":":"},{"ind":1,"ty":"sh","ks":{"a":0,"k":{"i":[[-5.237,0],[0,5.237],[5.237,0],[0,-5.237]],"o":[[5.237,0],[0,-5.237],[-5.237,0],[0,5.237]],"v":[[14.099,1.41],[23.666,-8.157],[14.099,-17.725],[4.532,-8.157]],"c":true}},"nm":":"}],"nm":":"}]},"fFamily":"Gilroy"},{"ch":"W","size":20,"style":"ExtraBold","w":99.8,"data":{"shapes":[{"ty":"gr","it":[{"ind":0,"ty":"sh","ks":{"a":0,"k":{"i":[[0,0],[0,0],[0,0],[0,0],[0,0],[0,0],[0,0],[0,0],[0,0],[0,0],[0,0],[0,0],[0,0]],"o":[[0,0],[0,0],[0,0],[0,0],[0,0],[0,0],[0,0],[0,0],[0,0],[0,0],[0,0],[0,0],[0,0]],"v":[[20.444,0],[38.773,0],[50.253,-41.592],[61.734,0],[80.063,0],[99.5,-70.496],[82.581,-70.496],[70.395,-21.149],[56.799,-70.496],[43.707,-70.496],[30.112,-21.149],[17.926,-70.496],[1.007,-70.496]],"c":true}},"nm":"W"}],"nm":"W"}]},"fFamily":"Gilroy"},{"ch":"e","size":20,"style":"ExtraBold","w":57.5,"data":{"shapes":[{"ty":"gr","it":[{"ind":0,"ty":"sh","ks":{"a":0,"k":{"i":[[1.913,5.237],[0,0],[0,2.115],[14.703,0],[0,-15.005],[-17.221,0],[-4.935,6.848],[0,0],[4.129,0]],"o":[[0,0],[0.403,-1.913],[0,-15.207],[-15.912,0],[0,15.005],[9.567,0],[0,0],[-2.014,2.216],[-5.539,0]],"v":[[19.034,-19.135],[54.785,-19.135],[55.389,-25.177],[29.81,-51.764],[3.021,-25.177],[30.917,1.41],[52.872,-8.963],[40.787,-15.912],[31.119,-12.085]],"c":true}},"nm":"e"},{"ind":1,"ty":"sh","ks":{"a":0,"k":{"i":[[0,0],[-5.74,0],[-1.611,-5.841]],"o":[[1.41,-5.136],[4.532,0],[0,0]],"v":[[18.732,-30.414],[29.709,-38.37],[40.384,-30.414]],"c":true}},"nm":"e"}],"nm":"e"}]},"fFamily":"Gilroy"},{"ch":"â","size":20,"style":"ExtraBold","w":29,"data":{"shapes":[{"ty":"gr","it":[{"ind":0,"ty":"sh","ks":{"a":0,"k":{"i":[[0,0],[0,0],[0,0],[0,0]],"o":[[0,0],[0,0],[0,0],[0,0]],"v":[[24.673,-70.496],[8.56,-70.496],[4.532,-40.787],[16.617,-40.787]],"c":true}},"nm":"â"}],"nm":"â"}]},"fFamily":"Gilroy"},{"ch":"r","size":20,"style":"ExtraBold","w":37,"data":{"shapes":[{"ty":"gr","it":[{"ind":0,"ty":"sh","ks":{"a":0,"k":{"i":[[2.014,-6.747],[0,0],[0,0],[0,0],[0,0],[0,0],[-6.244,-1.007],[0,0]],"o":[[0,0],[0,0],[0,0],[0,0],[0,0],[0,-9.97],[0,0],[-6.345,0]],"v":[[20.645,-41.391],[20.645,-50.354],[5.539,-50.354],[5.539,0],[20.645,0],[20.645,-22.76],[35.751,-34.241],[35.751,-51.361]],"c":true}},"nm":"r"}],"nm":"r"}]},"fFamily":"Gilroy"},{"ch":"s","size":20,"style":"ExtraBold","w":43.8,"data":{"shapes":[{"ty":"gr","it":[{"ind":0,"ty":"sh","ks":{"a":0,"k":{"i":[[0,5.74],[-2.618,0],[-1.41,-2.618],[0,0],[8.157,0],[0,-10.977],[0,-5.539],[3.625,0],[1.309,3.827],[0,0],[-10.071,0],[0,11.581]],"o":[[0,-1.813],[3.323,0],[0,0],[-4.23,-7.15],[-10.474,0],[0,17.422],[0,2.014],[-4.431,0],[0,0],[3.928,8.157],[10.876,0],[0,-18.631]],"v":[[19.839,-35.651],[24.069,-38.47],[30.817,-34.039],[43.707,-40.988],[24.069,-51.764],[4.33,-35.248],[29.105,-15.207],[23.666,-12.085],[15.106,-18.027],[2.014,-10.574],[23.666,1.41],[44.614,-15.106]],"c":true}},"nm":"s"}],"nm":"s"}]},"fFamily":"Gilroy"},{"ch":"o","size":20,"style":"ExtraBold","w":59,"data":{"shapes":[{"ty":"gr","it":[{"ind":0,"ty":"sh","ks":{"a":0,"k":{"i":[[-14.804,0],[0,15.005],[14.804,0],[0,-15.005]],"o":[[14.804,0],[0,-15.005],[-14.804,0],[0,15.005]],"v":[[29.709,1.41],[56.396,-25.177],[29.709,-51.764],[3.021,-25.177]],"c":true}},"nm":"o"},{"ind":1,"ty":"sh","ks":{"a":0,"k":{"i":[[6.546,0],[0,7.15],[-6.546,0],[0,-7.15]],"o":[[-6.546,0],[0,-7.15],[6.546,0],[0,7.15]],"v":[[29.709,-13.293],[18.127,-25.177],[29.709,-37.061],[41.29,-25.177]],"c":true}},"nm":"o"}],"nm":"o"}]},"fFamily":"Gilroy"},{"ch":"i","size":20,"style":"ExtraBold","w":26,"data":{"shapes":[{"ty":"gr","it":[{"ind":0,"ty":"sh","ks":{"a":0,"k":{"i":[[-4.935,0],[0,4.935],[4.935,0],[0,-4.935]],"o":[[4.935,0],[0,-4.935],[-4.935,0],[0,4.935]],"v":[[13.092,-54.785],[22.156,-63.849],[13.092,-72.913],[4.028,-63.849]],"c":true}},"nm":"i"},{"ind":1,"ty":"sh","ks":{"a":0,"k":{"i":[[0,0],[0,0],[0,0],[0,0]],"o":[[0,0],[0,0],[0,0],[0,0]],"v":[[5.539,0],[20.645,0],[20.645,-50.354],[5.539,-50.354]],"c":true}},"nm":"i"}],"nm":"i"}]},"fFamily":"Gilroy"},{"ch":"y","size":20,"style":"ExtraBold","w":53,"data":{"shapes":[{"ty":"gr","it":[{"ind":0,"ty":"sh","ks":{"a":0,"k":{"i":[[0,0],[0,0],[0,0],[0,0],[0,0],[7.05,0],[0,0],[-5.64,16.013],[0,0]],"o":[[0,0],[0,0],[0,0],[0,0],[-2.216,6.143],[0,0],[14.099,0.705],[0,0],[0,0]],"v":[[37.262,-50.354],[27.795,-19.537],[16.617,-50.354],[0,-50.354],[20.041,-2.316],[7.452,6.042],[7.452,20.142],[36.154,-1.511],[53.375,-50.354]],"c":true}},"nm":"y"}],"nm":"y"}]},"fFamily":"Gilroy"},{"ch":"n","size":20,"style":"ExtraBold","w":58.3,"data":{"shapes":[{"ty":"gr","it":[{"ind":0,"ty":"sh","ks":{"a":0,"k":{"i":[[10.172,0],[2.719,-3.726],[0,0],[0,0],[0,0],[0,0],[0,0],[-5.539,0],[0,-6.244],[0,0],[0,0],[0,0]],"o":[[-6.647,0],[0,0],[0,0],[0,0],[0,0],[0,0],[0,-7.15],[4.834,0],[0,0],[0,0],[0,0],[0,-13.596]],"v":[[35.046,-51.764],[20.645,-45.621],[20.645,-50.354],[5.539,-50.354],[5.539,0],[20.645,0],[20.645,-27.493],[30.011,-37.866],[38.773,-28.702],[38.773,0],[53.879,0],[53.879,-30.917]],"c":true}},"nm":"n"}],"nm":"n"}]},"fFamily":"Gilroy"},{"ch":"9","size":20,"style":"ExtraBold","w":56,"data":{"shapes":[{"ty":"gr","it":[{"ind":0,"ty":"sh","ks":{"a":0,"k":{"i":[[0,5.438],[15.61,0],[0,-14.603],[-13.998,-1.108],[0,0],[0,0],[0,0]],"o":[[0,-14.603],[-15.509,0],[0,13.696],[0,0],[0,0],[0,0],[2.618,-3.928]],"v":[[54.382,-47.031],[28.198,-71.906],[2.014,-47.031],[25.479,-22.256],[10.172,0],[28.702,0],[50.253,-32.73]],"c":true}},"nm":"9"},{"ind":1,"ty":"sh","ks":{"a":0,"k":{"i":[[0,6.143],[-5.338,0],[0,-6.244],[5.438,0]],"o":[[0,-6.143],[5.438,0],[0,6.244],[-5.338,0]],"v":[[18.127,-47.031],[28.198,-56.799],[38.269,-47.031],[28.198,-37.262]],"c":true}},"nm":"9"}],"nm":"9"}]},"fFamily":"Gilroy"},{"ch":"0","size":20,"style":"ExtraBold","w":63,"data":{"shapes":[{"ty":"gr","it":[{"ind":0,"ty":"sh","ks":{"a":0,"k":{"i":[[-18.228,0],[0,21.753],[18.228,0],[0,-21.753]],"o":[[18.228,0],[0,-21.753],[-18.228,0],[0,21.753]],"v":[[31.723,1.41],[60.425,-35.248],[31.723,-71.906],[3.021,-35.248]],"c":true}},"nm":"0"},{"ind":1,"ty":"sh","ks":{"a":0,"k":{"i":[[8.459,0],[0,13.596],[-8.459,0],[0,-13.596]],"o":[[-8.459,0],[0,-13.596],[8.459,0],[0,13.596]],"v":[[31.723,-14.301],[19.135,-35.248],[31.723,-56.195],[44.312,-35.248]],"c":true}},"nm":"0"}],"nm":"0"}]},"fFamily":"Gilroy"}]}